<?xml version="1.0" ?>
<all>
	<s>33</s>
	<t>51</t>
	<time_core>0.015946626663208008</time_core>
	<time_heur_node>0.005341768264770508</time_heur_node>
	<time_heur_dist>0.006217002868652344</time_heur_dist>
	<pathlen_bh_avg_node>5.6</pathlen_bh_avg_node>
	<pathlen_bh_avg_dist>6.312593720940429</pathlen_bh_avg_dist>
	<pathlen_ah_node_avg_node>5.4</pathlen_ah_node_avg_node>
	<pathlen_ah_node_min_node>3</pathlen_ah_node_min_node>
	<pathlen_ah_node_max_node>7</pathlen_ah_node_max_node>
	<pathlen_ah_node_avg_dist>6.433703976033226</pathlen_ah_node_avg_dist>
	<pathlen_ah_node_min_dist>2.8284271247461903</pathlen_ah_node_min_dist>
	<pathlen_ah_node_max_dist>9.84161925296378</pathlen_ah_node_max_dist>
	<pathlen_ah_dist_avg_node>5.0</pathlen_ah_dist_avg_node>
	<pathlen_ah_dist_min_node>3</pathlen_ah_dist_min_node>
	<pathlen_ah_dist_max_node>7</pathlen_ah_dist_max_node>
	<pathlen_ah_dist_avg_dist>6.033703976033225</pathlen_ah_dist_avg_dist>
	<pathlen_ah_dist_min_dist>2.8284271247461903</pathlen_ah_dist_min_dist>
	<pathlen_ah_dist_max_dist>9.84161925296378</pathlen_ah_dist_max_dist>
	<s_t_connectivity>5</s_t_connectivity>
	<k>5</k>
	<shortest_path_len_node>3</shortest_path_len_node>
	<shortest_path_len_dist>2.8284271247461903</shortest_path_len_dist>
	<srlg_intersections>
		<item>1</item>
		<item>3</item>
		<item>2</item>
		<item>1</item>
		<item>2</item>
	</srlg_intersections>
	<two_shorterst_srlg_node>8</two_shorterst_srlg_node>
	<two_shorterst_srlg_dist>6.82842712474619</two_shorterst_srlg_dist>
	<two_shortest_flow_dist>6.82842712474619e-06</two_shortest_flow_dist>
	<two_shortest_flow_node>10</two_shortest_flow_node>
</all>
